atollas/__init__.py
atollas/aggregations.py
atollas/dataframe.py
atollas/dataframe_schema.py
atollas/io.py
atollas/types.py
atollas-0.0.3.dist-info/WHEEL
atollas-0.0.3.dist-info/METADATA
atollas-0.0.3.dist-info/RECORD
