Metadata-Version: 2.1
Name: atollas
Version: 0.0.3
Summary: Add your description here
Requires-Python: >= 3.10
Requires-Dist: pandas>=2
Requires-Dist: pyarrow>=15.0.1
